adafruit_s35710.py
adafruit_circuitpython_s35710-1.0.6.dist-info/licenses/LICENSE
adafruit_circuitpython_s35710-1.0.6.dist-info/METADATA
adafruit_circuitpython_s35710-1.0.6.dist-info/WHEEL
adafruit_circuitpython_s35710-1.0.6.dist-info/top_level.txt
adafruit_circuitpython_s35710-1.0.6.dist-info/RECORD
